iracing_league_session_auditor/__init__.py
iracing_league_session_auditor/__main__.py
iracing_league_session_auditor/cli.py
iracing_league_session_auditor/exceptions.py
iracing_league_session_auditor/modules/__init__.py
iracing_league_session_auditor/modules/api.py
iracing_league_session_auditor/modules/api_pull.py
iracing_league_session_auditor/modules/cron_matcher.py
iracing_league_session_auditor/modules/notifier.py
iracing_league_session_auditor/modules/session_validator.py
iracing_league_session_auditor/modules/state_manager.py
iracing_league_session_auditor/modules/types.py
iracing_league_session_auditor/tests/__init__.py
iracing_league_session_auditor/tests/test_api_state_interaction.py
iracing_league_session_auditor/tests/test_cron_matcher.py
iracing_league_session_auditor/tests/test_notifier.py
iracing_league_session_auditor/tests/test_validator.py
iracing_league_session_auditor/tests/test_validator_advanced.py
iracing_league_session_auditor/tests/test_validator_comparisons.py
iracing_league_session_auditor-1.1.3.dist-info/METADATA
iracing_league_session_auditor-1.1.3.dist-info/WHEEL
iracing_league_session_auditor-1.1.3.dist-info/entry_points.txt
iracing_league_session_auditor-1.1.3.dist-info/licenses/LICENSE
iracing_league_session_auditor-1.1.3.dist-info/RECORD
