Metadata-Version: 2.4
Name: iracing_league_session_auditor
Version: 1.1.3
Summary: A tool to validate and audit iRacing league sessions against expected parameters
Project-URL: Homepage, https://github.com/username/iracing_league_session_auditor
Project-URL: Bug Tracker, https://github.com/username/iracing_league_session_auditor/issues
Author-email: Tyler Agostino <tyleragostino@gmail.com>
License:                     GNU GENERAL PUBLIC LICENSE
License-File: LICENSE
Classifier: License :: OSI Approved :: MIT License
Classifier: Operating System :: OS Independent
Classifier: Programming Language :: Python :: 3
Classifier: Programming Language :: Python :: 3.8
Classifier: Programming Language :: Python :: 3.9
Classifier: Programming Language :: Python :: 3.10
Classifier: Programming Language :: Python :: 3.11
Classifier: Programming Language :: Python :: 3.12
Requires-Python: >=3.8
Requires-Dist: pandas>=1.3.0
Requires-Dist: requests>=2.26.0
Provides-Extra: dev
Requires-Dist: black>=23.0.0; extra == 'dev'
Requires-Dist: flake8>=6.0.0; extra == 'dev'
Requires-Dist: mypy>=1.0.0; extra == 'dev'
Requires-Dist: pytest>=7.0.0; extra == 'dev'
